outlier_removal_yash_saxena/outlier.py
outlier_removal_yash_saxena-1.0.2.dist-info/LICENSE
outlier_removal_yash_saxena-1.0.2.dist-info/METADATA
outlier_removal_yash_saxena-1.0.2.dist-info/WHEEL
outlier_removal_yash_saxena-1.0.2.dist-info/entry_points.txt
outlier_removal_yash_saxena-1.0.2.dist-info/top_level.txt
outlier_removal_yash_saxena-1.0.2.dist-info/RECORD
