Metadata-Version: 2.1
Name: outlier-removal-yash-saxena
Version: 1.0.2
Summary: A Python pip package to remove outliers from the dataset
Home-page: https://github.com/yashsaxena972/outlier-removal
Author: Yash Saxena
Author-email: yash972saxena@gmail.com
License: MIT
Platform: UNKNOWN
Classifier: License :: OSI Approved :: MIT License
Classifier: Programming Language :: Python :: 3
Classifier: Programming Language :: Python :: 3.7
Requires-Dist: numpy
Requires-Dist: pandas
